snip_copy/__init__.py
snip_copy/__main__.py
snip_copy/copy_file.py
snip_copy/parse.py
snip_copy/snip.py
snip_copy/ipynb/__init__.py
snip_copy/ipynb/copy_file.py
snip_copy/ipynb/json_ipynb.py
snip_copy-0.0.3.dist-info/LICENSE
snip_copy-0.0.3.dist-info/METADATA
snip_copy-0.0.3.dist-info/WHEEL
snip_copy-0.0.3.dist-info/top_level.txt
snip_copy-0.0.3.dist-info/RECORD
