Metadata-Version: 2.1
Name: snip-copy
Version: 0.0.3
Summary: snips lines from text files (automate creation of student copy from solution)
Author-email: Matt Higger <matt.higger@gmail.com>
License: GNU GENERAL PUBLIC LICENSE
Project-URL: Homepage, https://github.com/matthigger/snip_copy
Classifier: Programming Language :: Python :: 3
Classifier: Operating System :: OS Independent
Requires-Python: >=3.10
License-File: LICENSE
